autonetkit/__init__.py
autonetkit/entry.py
autonetkit/compile/__init__.py
autonetkit/compile/node_compiler.py
autonetkit/compile/node/__init__.py
autonetkit/compile/node/base.py
autonetkit/compile/node/linux_host.py
autonetkit/compile/node/quagga.py
autonetkit/compile/platform/__init__.py
autonetkit/compile/platform/base.py
autonetkit/compile/platform/kathara.py
autonetkit/design/__init__.py
autonetkit/design/builder.py
autonetkit/design/layer2.py
autonetkit/design/routing.py
autonetkit/design/ip_addressing/__init__.py
autonetkit/design/ip_addressing/general.py
autonetkit/design/ip_addressing/ipv4.py
autonetkit/design/utils/__init__.py
autonetkit/design/utils/filters.py
autonetkit/design/utils/general.py
autonetkit/design/utils/graph_utils.py
autonetkit/design/validation/__init__.py
autonetkit/design/validation/validation.py
autonetkit/example/__init__.py
autonetkit/example/mixed.graphml
autonetkit/example/small_internet.graphml
autonetkit/load/__init__.py
autonetkit/load/common.py
autonetkit/load/load_graphml.py
autonetkit/load/model.py
autonetkit/load/preprocess.py
autonetkit/load/simplified.py
autonetkit/load/validation.py
autonetkit/network_model/__init__.py
autonetkit/network_model/exceptions.py
autonetkit/network_model/link.py
autonetkit/network_model/network_model.py
autonetkit/network_model/node.py
autonetkit/network_model/path.py
autonetkit/network_model/port.py
autonetkit/network_model/topology.py
autonetkit/network_model/types.py
autonetkit/packager/__init__.py
autonetkit/packager/base.py
autonetkit/packager/kathara.py
autonetkit/packager/mapping.py
autonetkit/packager/utils.py
autonetkit/render/__init__.py
autonetkit/render/exceptions.py
autonetkit/render/renderer.py
autonetkit/render/types.py
autonetkit/render/node/__init__.py
autonetkit/render/node/base.py
autonetkit/render/node/linux_host.py
autonetkit/render/node/quagga.py
autonetkit/render/platform/__init__.py
autonetkit/render/platform/base.py
autonetkit/render/platform/kathara.py
autonetkit-0.12.3.dist-info/LICENCE.txt
autonetkit-0.12.3.dist-info/METADATA
autonetkit-0.12.3.dist-info/WHEEL
autonetkit-0.12.3.dist-info/entry_points.txt
autonetkit-0.12.3.dist-info/top_level.txt
autonetkit-0.12.3.dist-info/RECORD
