Metadata-Version: 2.1
Name: autonetkit
Version: 0.12.3
Summary: Automatic configuration generation
Home-page: http://www.autonetkit.org
Author: Simon Knight
Author-email: simon.knight@gmail.com
License: UNKNOWN
Download-URL: http://pypi.python.org/pypi/autonetkit
Platform: UNKNOWN
Classifier: Programming Language :: Python
Classifier: Development Status :: 4 - Beta
Classifier: Intended Audience :: Science/Research
Classifier: Intended Audience :: System Administrators
Classifier: Intended Audience :: Telecommunications Industry
Classifier: License :: OSI Approved :: BSD License
Classifier: Operating System :: MacOS :: MacOS X
Classifier: Operating System :: POSIX :: Linux
Classifier: Topic :: System :: Networking
Classifier: Topic :: System :: Software Distribution
Classifier: Topic :: Scientific/Engineering :: Mathematics
Requires-Dist: netaddr
Requires-Dist: networkx
Requires-Dist: Jinja2
Requires-Dist: aiohttp
Requires-Dist: aiohttp-jinja2
Requires-Dist: requests
Requires-Dist: pydantic
